{
  "info": {
    "name": "ECommerce API Collection",
    "description": "Complete collection of ECommerce API endpoints for products, categories, and sales management",
    "schema": "https://schema.getpostman.com/json/collection/v2.1.0/collection.json"
  },
  "item": [
    {
      "name": "Products",
      "item": [
        {
          "name": "Get All Products",
          "request": {
            "method": "GET",
            "header": [],
            "url": {
              "raw": "{{baseUrl}}/api/products?page=1&pageSize=10",
              "host": ["{{baseUrl}}"],
              "path": ["api", "products"],
              "query": [
                {
                  "key": "page",
                  "value": "1"
                },
                {
                  "key": "pageSize",
                  "value": "10"
                }
              ]
            },
            "description": "Retrieve all products with optional pagination"
          },
          "response": [
            {
              "name": "Successful Response",
              "originalRequest": {
                "method": "GET",
                "header": [],
                "url": {
                  "raw": "{{baseUrl}}/api/products?page=1&pageSize=10",
                  "host": ["{{baseUrl}}"],
                  "path": ["api", "products"],
                  "query": [
                    {
                      "key": "page",
                      "value": "1"
                    },
                    {
                      "key": "pageSize",
                      "value": "10"
                    }
                  ]
                }
              },
              "status": "OK",
              "code": 200,
              "_postman_previewlanguage": "json",
              "header": [
                {
                  "key": "Content-Type",
                  "value": "application/json"
                }
              ],
              "cookie": [],
              "body": "{\n  \"requestFailed\": false,\n  \"responseCode\": 200,\n  \"errorMessage\": \"\",\n  \"data\": [\n    {\n      \"productId\": 1,\n      \"name\": \"Sample Product\",\n      \"description\": \"Product description\",\n      \"price\": 29.99,\n      \"stock\": 100,\n      \"isActive\": true,\n      \"categoryId\": 1,\n      \"category\": {\n        \"categoryId\": 1,\n        \"name\": \"Electronics\",\n        \"description\": \"Electronic devices\"\n      },\n      \"isDeleted\": false,\n      \"deletedAt\": null\n    }\n  ],\n  \"currentPage\": 1,\n  \"pageSize\": 10,\n  \"totalCount\": 25,\n  \"totalPages\": 3,\n  \"hasNextPage\": true,\n  \"hasPreviousPage\": false\n}"
            }
          ]
        },
        {
          "name": "Get Product by ID",
          "request": {
            "method": "GET",
            "header": [],
            "url": {
              "raw": "{{baseUrl}}/api/products/1",
              "host": ["{{baseUrl}}"],
              "path": ["api", "products", "1"]
            },
            "description": "Retrieve a specific product by ID"
          }
        },
        {
          "name": "Get Products by Category",
          "request": {
            "method": "GET",
            "header": [],
            "url": {
              "raw": "{{baseUrl}}/api/products/category/1",
              "host": ["{{baseUrl}}"],
              "path": ["api", "products", "category", "1"]
            },
            "description": "Retrieve products filtered by category ID"
          }
        },
        {
          "name": "Create Product",
          "request": {
            "method": "POST",
            "header": [
              {
                "key": "Content-Type",
                "value": "application/json"
              }
            ],
            "body": {
              "mode": "raw",
              "raw": "{\n  \"payload\": {\n    \"name\": \"New Product\",\n    \"description\": \"Product description\",\n    \"price\": 29.99,\n    \"stock\": 100,\n    \"isActive\": true,\n    \"categoryId\": 1\n  }\n}"
            },
            "url": {
              "raw": "{{baseUrl}}/api/products",
              "host": ["{{baseUrl}}"],
              "path": ["api", "products"]
            },
            "description": "Create a new product"
          }
        },
        {
          "name": "Update Product",
          "request": {
            "method": "PUT",
            "header": [
              {
                "key": "Content-Type",
                "value": "application/json"
              }
            ],
            "body": {
              "mode": "raw",
              "raw": "{\n  \"payload\": {\n    \"name\": \"Updated Product\",\n    \"description\": \"Updated description\",\n    \"price\": 39.99,\n    \"stock\": 150,\n    \"isActive\": true,\n    \"categoryId\": 1\n  }\n}"
            },
            "url": {
              "raw": "{{baseUrl}}/api/products/1",
              "host": ["{{baseUrl}}"],
              "path": ["api", "products", "1"]
            },
            "description": "Update an existing product"
          }
        },
        {
          "name": "Delete Product",
          "request": {
            "method": "DELETE",
            "header": [],
            "url": {
              "raw": "{{baseUrl}}/api/products/1",
              "host": ["{{baseUrl}}"],
              "path": ["api", "products", "1"]
            },
            "description": "Soft delete a product"
          }
        },
        {
          "name": "Get Deleted Products",
          "request": {
            "method": "GET",
            "header": [],
            "url": {
              "raw": "{{baseUrl}}/api/products/deleted",
              "host": ["{{baseUrl}}"],
              "path": ["api", "products", "deleted"]
            },
            "description": "Retrieve all soft-deleted products"
          }
        },
        {
          "name": "Restore Product",
          "request": {
            "method": "POST",
            "header": [],
            "url": {
              "raw": "{{baseUrl}}/api/products/1/restore",
              "host": ["{{baseUrl}}"],
              "path": ["api", "products", "1", "restore"]
            },
            "description": "Restore a soft-deleted product"
          }
        }
      ]
    },
    {
      "name": "Categories",
      "item": [
        {
          "name": "Get All Categories",
          "request": {
            "method": "GET",
            "header": [],
            "url": {
              "raw": "{{baseUrl}}/api/categories",
              "host": ["{{baseUrl}}"],
              "path": ["api", "categories"]
            },
            "description": "Retrieve all categories"
          }
        },
        {
          "name": "Get Category by ID",
          "request": {
            "method": "GET",
            "header": [],
            "url": {
              "raw": "{{baseUrl}}/api/categories/1",
              "host": ["{{baseUrl}}"],
              "path": ["api", "categories", "1"]
            },
            "description": "Retrieve a specific category by ID"
          }
        },
        {
          "name": "Create Category",
          "request": {
            "method": "POST",
            "header": [
              {
                "key": "Content-Type",
                "value": "application/json"
              }
            ],
            "body": {
              "mode": "raw",
              "raw": "{\n  \"payload\": {\n    \"name\": \"New Category\",\n    \"description\": \"Category description\"\n  }\n}"
            },
            "url": {
              "raw": "{{baseUrl}}/api/categories",
              "host": ["{{baseUrl}}"],
              "path": ["api", "categories"]
            },
            "description": "Create a new category"
          }
        },
        {
          "name": "Update Category",
          "request": {
            "method": "PUT",
            "header": [
              {
                "key": "Content-Type",
                "value": "application/json"
              }
            ],
            "body": {
              "mode": "raw",
              "raw": "{\n  \"payload\": {\n    \"name\": \"Updated Category\",\n    \"description\": \"Updated description\"\n  }\n}"
            },
            "url": {
              "raw": "{{baseUrl}}/api/categories/1",
              "host": ["{{baseUrl}}"],
              "path": ["api", "categories", "1"]
            },
            "description": "Update an existing category"
          }
        },
        {
          "name": "Delete Category",
          "request": {
            "method": "DELETE",
            "header": [],
            "url": {
              "raw": "{{baseUrl}}/api/categories/1",
              "host": ["{{baseUrl}}"],
              "path": ["api", "categories", "1"]
            },
            "description": "Soft delete a category"
          }
        },
        {
          "name": "Get Deleted Categories",
          "request": {
            "method": "GET",
            "header": [],
            "url": {
              "raw": "{{baseUrl}}/api/categories/deleted",
              "host": ["{{baseUrl}}"],
              "path": ["api", "categories", "deleted"]
            },
            "description": "Retrieve all soft-deleted categories"
          }
        },
        {
          "name": "Restore Category",
          "request": {
            "method": "POST",
            "header": [],
            "url": {
              "raw": "{{baseUrl}}/api/categories/1/restore",
              "host": ["{{baseUrl}}"],
              "path": ["api", "categories", "1", "restore"]
            },
            "description": "Restore a soft-deleted category"
          }
        }
      ]
    },
    {
      "name": "Sales",
      "item": [
        {
          "name": "Get All Sales",
          "request": {
            "method": "GET",
            "header": [],
            "url": {
              "raw": "{{baseUrl}}/api/sales?page=1&pageSize=10",
              "host": ["{{baseUrl}}"],
              "path": ["api", "sales"],
              "query": [
                {
                  "key": "page",
                  "value": "1"
                },
                {
                  "key": "pageSize",
                  "value": "10"
                }
              ]
            },
            "description": "Retrieve all sales with optional pagination"
          },
          "response": [
            {
              "name": "Successful Response",
              "originalRequest": {
                "method": "GET",
                "header": [],
                "url": {
                  "raw": "{{baseUrl}}/api/sales?page=1&pageSize=10",
                  "host": ["{{baseUrl}}"],
                  "path": ["api", "sales"],
                  "query": [
                    {
                      "key": "page",
                      "value": "1"
                    },
                    {
                      "key": "pageSize",
                      "value": "10"
                    }
                  ]
                }
              },
              "status": "OK",
              "code": 200,
              "_postman_previewlanguage": "json",
              "header": [
                {
                  "key": "Content-Type",
                  "value": "application/json"
                }
              ],
              "cookie": [],
              "body": "{\n  \"requestFailed\": false,\n  \"responseCode\": 200,\n  \"errorMessage\": \"\",\n  \"data\": [\n    {\n      \"saleId\": 1,\n      \"saleDate\": \"2024-01-15T10:00:00Z\",\n      \"totalAmount\": 59.98,\n      \"saleItems\": [\n        {\n          \"saleItemId\": 1,\n          \"quantity\": 2,\n          \"unitPrice\": 29.99,\n          \"product\": {\n            \"productId\": 1,\n            \"name\": \"Sample Product\",\n            \"description\": \"Product description\",\n            \"price\": 29.99,\n            \"stock\": 100,\n            \"isActive\": true\n          }\n        }\n      ],\n      \"isDeleted\": false,\n      \"deletedAt\": null\n    }\n  ],\n  \"currentPage\": 1,\n  \"pageSize\": 10,\n  \"totalCount\": 45,\n  \"totalPages\": 5,\n  \"hasNextPage\": true,\n  \"hasPreviousPage\": false\n}"
            }
          ]
        },
        {
          "name": "Get Sale by ID",
          "request": {
            "method": "GET",
            "header": [],
            "url": {
              "raw": "{{baseUrl}}/api/sales/1",
              "host": ["{{baseUrl}}"],
              "path": ["api", "sales", "1"]
            },
            "description": "Retrieve a specific sale by ID"
          }
        },
        {
          "name": "Get Sales with Deleted Products",
          "request": {
            "method": "GET",
            "header": [],
            "url": {
              "raw": "{{baseUrl}}/api/sales/with-deleted-products",
              "host": ["{{baseUrl}}"],
              "path": ["api", "sales", "with-deleted-products"]
            },
            "description": "Retrieve sales including historical data with deleted products"
          }
        },
        {
          "name": "Create Sale",
          "request": {
            "method": "POST",
            "header": [
              {
                "key": "Content-Type",
                "value": "application/json"
              }
            ],
            "body": {
              "mode": "raw",
              "raw": "{\n  \"payload\": {\n    \"saleDate\": \"2024-01-15T10:00:00Z\",\n    \"totalAmount\": 59.98,\n    \"saleItems\": [\n      {\n        \"productId\": 1,\n        \"quantity\": 2,\n        \"unitPrice\": 29.99\n      }\n    ]\n  }\n}"
            },
            "url": {
              "raw": "{{baseUrl}}/api/sales",
              "host": ["{{baseUrl}}"],
              "path": ["api", "sales"]
            },
            "description": "Create a new sale"
          }
        }
      ]
    }
  ],
  "variable": [
    {
      "key": "baseUrl",
      "value": "https://localhost:5001",
      "type": "string"
    }
  ]
}
